{
  "intents": [
    {
      "tag": "greeting",
      "questions": [
        "Hi",
        "How are you?",
        "Is anyone there?",
        "Hello",
        "Good day",
        "What's up",
        "how are ya",
        "heyy",
        "whatsup",
        "??? ??? ??",
        "Hey there",
        "Greetings",
        "Hey",
        "Hey!",
        "Good morning",
        "Good afternoon",
        "How's it going?",
        "Hey, how's everything?",
        "Yo!",
        "Hiya!",
        "Hey, what's new?",
        "Hey, how's your day?",
        "What's happening?",
        "Hey, howdy!",
        "Hey, stranger!",
        "Hey, long time no see!",
        "Hey, it's been a while!",
        "Hey, how have you been?"
      ],
      "responses": [
        "Hello!",
        "Good to see you again!",
        "Hi there, how can I help?",
        "Hey!",
        "Greetings! How can I assist you?",
        "Hi! How's your day going?",
        "Hey there! What can I do for you?",
        "Hello! What brings you here today?",
        "Hey! Nice to see you. What's up?",
        "Hi! Ready to get started?",
        "Hey! How can I assist you today?",
        "Hello! How can I be of service?",
        "Hey! How's everything going?",
        "Hi there! What's new with you?",
        "Hello! How have you been?"
      ],
      "context_set": ""
    },

    {
      "tag": "creator",
      "questions": [
        "what is the name of your developers",
        "what is the name of your creators",
        "what is the name of the developers",
        "what is the name of the creators",
        "who created you",
        "your developers",
        "your creators",
        "who are your developers",
        "developers",
        "you are made by",
        "you are made by whom",
        "who created you",
        "who create you",
        "creators",
        "who made you",
        "who designed you"
      ],
      "responses": ["Made By: Team Emoti-Commerce"],
      "context_set": ""
    },
    {
      "tag": "name",
      "questions": [
        "name",
        "your name",
        "do you have a name",
        "what are you called",
        "what is your name",
        "what should I call you",
        "whats your name?",
        "what are you",
        "who are you",
        "who is this",
        "what am i chatting to",
        "who am i taking to",
        "what are you"
      ],
      "responses": [
        "You can call me Emoti-Commerce.",
        "I am your Emoti-Commerce Agent",
        "I am your Emoti-Commerce Agent and i am here to assist you in your shopping"
      ],
      "context_set": ""
    },
    {
      "tag": "products",
      "questions": [
        "products?",
        "What products do you offer?",
        "What can i buy?",
        "What items are available in your store?",
        "Can you tell me about the products you sell?",
        "What kind of products do you have?",
        "What are the available items?",
        "Which products are available for purchase?",
        "Tell me about the items in your shop.",
        "What do you have in stock?",
        "What products can I find on your website?",
        "List your available products, please."
      ],
      "responses": [
        "We offer a variety of products including Airpods Wireless Bluetooth Headphones, Sony Playstation 5, Amazon Echo Dot 3rd Generation, Cannon EOS 80D DSLR Camera, iPhone 13 Pro 256GB Memory, and Logitech G-Series Gaming Mouse.",
        "Our store provides an extensive range of products, such as Airpods Wireless Bluetooth Headphones, Sony Playstation 5, Amazon Echo Dot 3rd Generation, Cannon EOS 80D DSLR Camera, iPhone 13 Pro 256GB Memory, and Logitech G-Series Gaming Mouse.",
        "You can find a wide selection of products on our website, including Airpods Wireless Bluetooth Headphones, Sony Playstation 5, Amazon Echo Dot 3rd Generation, Cannon EOS 80D DSLR Camera, iPhone 13 Pro 256GB Memory, and Logitech G-Series Gaming Mouse."
      ],
      "context_set": ""
    },

    {
      "tag": "airpods_description",
      "questions": [
        "Airpods?",
        "Wireless Airpods?",
        "Airpods",
        "Bluetooth",
        "Wireless",
        "Description",
        "Features",
        "Details",
        "Tell me about Airpods.",
        "What can you tell me about Airpods?",
        "Describe Airpods Wireless Bluetooth Headphones.",
        "What are the features of Airpods?",
        "Can you give me details about Wireless Airpods?",
        "What is the description of Bluetooth Airpods?",
        "Give me information about Airpods Wireless Headphones."
      ],
      "responses": [
        "Airpods Wireless Bluetooth Headphones feature Bluetooth technology for wireless connectivity, high-quality AAC audio for an immersive listening experience, and a built-in microphone for taking calls while on the go."
      ],
      "context_set": ""
    },

    {
      "tag": "playstation_5_description",
      "questions": [
        "Playstation 5?",
        "PS5",
        "Sony PS5",
        "Description",
        "Features",
        "Details",
        "What is Playstation 5?",
        "What can you tell me about PS5?",
        "Describe Sony Playstation 5.",
        "What are the features of Playstation 5?",
        "Can you give me details about Sony PS5?",
        "Tell me about the Playstation 5 gaming console.",
        "What sets Sony Playstation 5 apart?",
        "Is Playstation 5 available?",
        "Where can I find Playstation 5?",
        "Playstation 5 in stock?",
        "Price of Playstation 5?",
        "Is PS5 compatible with PS4 games?",
        "Does PS5 support 4K gaming?",
        "How many controllers come with PS5?",
        "What accessories are compatible with Playstation 5?",
        "Are there any exclusive games for PS5?",
        "What is the storage capacity of Playstation 5?",
        "Can you tell me about the design of PS5?",
        "What are the specifications of Sony Playstation 5?",
        "Tell me about PS5's backward compatibility.",
        "Is PS5 backward compatible with PS3 games?",
        "Does PS5 have a disc drive?"
      ],
      "responses": [
        "The Sony Playstation 5 is a next-generation gaming console featuring powerful hardware, lightning-fast load times, immersive 3D audio, and an innovative DualSense controller for enhanced gameplay experiences."
      ],
      "context_set": ""
    },

    {
      "tag": "echo_dot_3rd_gen_description",
      "questions": [
        "Echo Dot?",
        "Amazon Echo Dot",
        "Echo Dot 3rd Generation",
        "Description",
        "Features",
        "Details",
        "What is Echo Dot?",
        "What can you tell me about Amazon Echo Dot?",
        "Describe Echo Dot 3rd Generation.",
        "What are the features of Echo Dot?",
        "Can you give me details about Amazon Echo Dot?",
        "Tell me about the Echo Dot smart speaker.",
        "Is Echo Dot available?",
        "Where can I find Echo Dot?",
        "Echo Dot in stock?",
        "Price of Echo Dot?",
        "Is Echo Dot compatible with Alexa?",
        "What can Echo Dot do?",
        "How does Echo Dot work?",
        "Does Echo Dot support voice commands?",
        "What music services are compatible with Echo Dot?",
        "Can Echo Dot control smart home devices?",
        "What is the size of Echo Dot?",
        "Can you tell me about the design of Echo Dot?",
        "What are the specifications of Amazon Echo Dot 3rd Generation?",
        "Tell me about Echo Dot's microphone array.",
        "What colors does Echo Dot come in?",
        "Does Echo Dot have a built-in speaker?"
      ],
      "responses": [
        "The Amazon Echo Dot 3rd Generation is a smart speaker powered by Alexa, offering voice control for music, news, weather, and more. It features a compact design, improved speaker quality, and compatibility with various smart home devices."
      ],
      "context_set": ""
    },

    {
      "tag": "eos_80d_description",
      "questions": [
        "Canon EOS 80D?",
        "EOS 80D",
        "Canon 80D DSLR",
        "Description",
        "Features",
        "Details",
        "What is Canon EOS 80D?",
        "What can you tell me about the Canon 80D DSLR camera?",
        "Describe the EOS 80D.",
        "What are the features of the Canon EOS 80D?",
        "Can you give me details about the EOS 80D DSLR camera?",
        "Tell me about the Canon 80D digital camera.",
        "Is the Canon EOS 80D available?",
        "Where can I find the Canon EOS 80D?",
        "Is the EOS 80D in stock?",
        "Price of Canon EOS 80D?",
        "What are the specs of the Canon 80D?",
        "What lenses are compatible with the EOS 80D?",
        "Does the EOS 80D support 4K video recording?",
        "What autofocus system does the Canon 80D have?",
        "Can the Canon EOS 80D connect to Wi-Fi?",
        "What is the resolution of the Canon 80D's sensor?",
        "Does the Canon 80D have a touchscreen?",
        "Tell me about the design of the Canon EOS 80D.",
        "What accessories come with the Canon 80D?",
        "Is the Canon 80D weather-sealed?",
        "Does the Canon EOS 80D have image stabilization?",
        "What type of memory card does the Canon 80D use?",
        "Can you tell me about the battery life of the Canon EOS 80D?"
      ],
      "responses": [
        "The Canon EOS 80D DSLR Camera is a versatile and powerful camera, featuring a 24.2-megapixel APS-C CMOS sensor, DIGIC 6 image processor, 45-point all cross-type AF system, and Full HD 1080p video recording capability. It offers built-in Wi-Fi and NFC connectivity, a vari-angle touchscreen LCD, and robust construction suitable for various photography needs."
      ],
      "context_set": ""
    },

    {
      "tag": "iphone_13_pro_description",
      "questions": [
        "iPhone 13 Pro?",
        "iPhone 13 Pro 256GB",
        "Describe iphone 13",
        "Features of iphone",
        "Details",
        "What is iPhone 13 Pro?",
        "What can you tell me about the iPhone 13 Pro 256GB?",
        "Describe the iPhone 13 Pro.",
        "What are the features of the iPhone 13 Pro?",
        "Can you give me details about the iPhone 13 Pro 256GB?",
        "Tell me about the iPhone 13 Pro smartphone.",
        "Is the iPhone 13 Pro available?",
        "Where can I find the iPhone 13 Pro?",
        "Is the iPhone 13 Pro in stock?",
        "Price of iPhone 13 Pro?",
        "What colors does the iPhone 13 Pro come in?",
        "What is the storage capacity of the iPhone 13 Pro?",
        "Does the iPhone 13 Pro support 5G?",
        "What is the screen size of the iPhone 13 Pro?",
        "What is the camera configuration of the iPhone 13 Pro?",
        "Can the iPhone 13 Pro shoot in Dolby Vision?",
        "What is the battery life of the iPhone 13 Pro?",
        "Does the iPhone 13 Pro have Face ID?",
        "Is the iPhone 13 Pro waterproof?",
        "What accessories come with the iPhone 13 Pro?",
        "Can you tell me about the design of the iPhone 13 Pro?",
        "Does the iPhone 13 Pro support wireless charging?",
        "What operating system does the iPhone 13 Pro run on?"
      ],
      "responses": [
        "The iPhone 13 Pro is a premium smartphone from Apple, featuring a stunning Super Retina XDR display, A15 Bionic chip, advanced camera system with ProRAW and ProRes video recording capabilities, and up to 256GB of storage. It offers 5G connectivity, Face ID for secure authentication, and a sleek design available in various colors."
      ],
      "context_set": ""
    },

    {
      "tag": "logitech_gaming_mouse_description",
      "questions": [
        "Logitech G-Series Gaming Mouse?",
        "Gaming Mouse",
        "Logitech G Mouse",
        "Describe logitech",
        "Features of logitech",
        "Details of logitech",
        "mouse",
        "What is Logitech G-Series Gaming Mouse?",
        "What can you tell me about the Logitech G-Series Gaming Mouse?",
        "Describe the Logitech G-Series Gaming Mouse.",
        "What are the features of the Logitech G-Series Gaming Mouse?",
        "Can you give me details about the Logitech G-Series Gaming Mouse?",
        "Tell me about the Logitech Gaming Mouse.",
        "Is the Logitech G-Series Gaming Mouse available?",
        "Where can I find the Logitech G-Series Gaming Mouse?",
        "Is the Gaming Mouse in stock?",
        "Price of Logitech G-Series Gaming Mouse?",
        "What is the DPI of the Logitech G-Series Gaming Mouse?",
        "Does the Logitech Gaming Mouse have customizable RGB lighting?",
        "What is the polling rate of the Logitech G-Series Gaming Mouse?",
        "How many buttons does the Logitech G-Series Gaming Mouse have?",
        "Is the Logitech Gaming Mouse suitable for FPS gaming?",
        "Does the Logitech G-Series Gaming Mouse come with software for customization?",
        "What is the weight of the Logitech G-Series Gaming Mouse?",
        "Can you tell me about the design of the Logitech Gaming Mouse?",
        "What type of sensor does the Logitech G-Series Gaming Mouse use?",
        "Does the Logitech Gaming Mouse support onboard memory?",
        "What accessories come with the Logitech G-Series Gaming Mouse?"
      ],
      "responses": [
        "The Logitech G-Series Gaming Mouse offers high performance and customization for gamers, featuring a high DPI sensor, customizable RGB lighting, programmable buttons, and ergonomic design for comfort during long gaming sessions."
      ],
      "context_set": ""
    },

    {
      "tag": "airpods_price",
      "questions": [
        "Airpods price?",
        "How much do Airpods cost?",
        "Price of Airpods?",
        "What is the price of Airpods?",
        "How expensive are Airpods?",
        "What's the cost of Airpods?",
        "Can you tell me the price of Airpods?",
        "What's the price tag on Airpods?",
        "Airpods - how much?",
        "What's the price range for Airpods?",
        "I'm interested in Airpods, what's the pricing?",
        "How affordable are Airpods?",
        "Are Airpods expensive?",
        "What's the price point for Airpods?",
        "I need to know the price of Airpods, can you help?",
        "Airpods pricing, please?",
        "What's the pricing like for Airpods?",
        "Do you have any information on Airpods pricing?",
        "Price for Airpods, please?",
        "Can you give me a quote for Airpods?",
        "How much do I need to budget for Airpods?",
        "Airpods - how much do they go for?",
        "Airpods - what's the cost?",
        "What's the market price for Airpods?",
        "How much money should I prepare for Airpods?",
        "What's the current price for Airpods?",
        "Can you provide pricing details for Airpods?",
        "Airpods - how much will it set me back?"
      ],
      "responses": [
        "The price of Airpods Wireless Bluetooth Headphones is $89.99."
      ],
      "context_set": ""
    },

    {
      "tag": "playstation_5_price",
      "questions": [
        "PS5 price?",
        "How much does Playstation 5 cost?",
        "Price of Playstation 5?",
        "What is the price of PS5?",
        "How expensive is Playstation 5?",
        "What's the cost of Playstation 5?",
        "Can you tell me the price of Playstation 5?",
        "What's the price tag on Playstation 5?",
        "Playstation 5 - how much?",
        "What's the price range for Playstation 5?",
        "I'm interested in Playstation 5, what's the pricing?",
        "How affordable is Playstation 5?",
        "Is Playstation 5 expensive?",
        "What's the price point for Playstation 5?",
        "I need to know the price of Playstation 5, can you help?",
        "Playstation 5 pricing, please?",
        "What's the pricing like for Playstation 5?",
        "Do you have any information on Playstation 5 pricing?",
        "Price for Playstation 5, please?",
        "Can you give me a quote for Playstation 5?",
        "How much do I need to budget for Playstation 5?",
        "Playstation 5 - how much does it go for?",
        "Playstation 5 - what's the cost?",
        "What's the market price for Playstation 5?",
        "How much money should I prepare for Playstation 5?",
        "What's the current price for Playstation 5?",
        "Can you provide pricing details for Playstation 5?",
        "Playstation 5 - how much will it set me back?"
      ],
      "responses": ["The price of Sony Playstation 5 is $399.99."],
      "context_set": ""
    },

    {
      "tag": "echo_dot_3rd_gen_price",
      "questions": [
        "Echo Dot price?",
        "How much is Echo Dot?",
        "Price of Echo Dot?",
        "What is the price of Echo Dot?",
        "How expensive is Echo Dot?",
        "What's the cost of Echo Dot?",
        "Can you tell me the price of Echo Dot?",
        "What's the price tag on Echo Dot?",
        "Echo Dot - how much?",
        "What's the price range for Echo Dot?",
        "I'm interested in Echo Dot, what's the pricing?",
        "How affordable is Echo Dot?",
        "Is Echo Dot expensive?",
        "What's the price point for Echo Dot?",
        "I need to know the price of Echo Dot, can you help?",
        "Echo Dot pricing, please?",
        "What's the pricing like for Echo Dot?",
        "Do you have any information on Echo Dot pricing?",
        "Price for Echo Dot, please?",
        "Can you give me a quote for Echo Dot?",
        "How much do I need to budget for Echo Dot?",
        "Echo Dot - how much does it go for?",
        "Echo Dot - what's the cost?",
        "What's the market price for Echo Dot?",
        "How much money should I prepare for Echo Dot?",
        "What's the current price for Echo Dot?",
        "Can you provide pricing details for Echo Dot?",
        "Echo Dot - how much will it set me back?"
      ],
      "responses": ["The price of Amazon Echo Dot 3rd Generation is $29.99."],
      "context_set": ""
    },

    {
      "tag": "eos_80d_price",
      "questions": [
        "Canon EOS 80D price?",
        "How much does EOS 80D cost?",
        "Price of Canon EOS 80D?",
        "What is the price of EOS 80D?",
        "How expensive is Canon EOS 80D?",
        "What's the cost of Canon EOS 80D?",
        "Can you tell me the price of Canon EOS 80D?",
        "What's the price tag on Canon EOS 80D?",
        "Canon EOS 80D - how much?",
        "What's the price range for Canon EOS 80D?",
        "I'm interested in Canon EOS 80D, what's the pricing?",
        "How affordable is Canon EOS 80D?",
        "Is Canon EOS 80D expensive?",
        "What's the price point for Canon EOS 80D?",
        "I need to know the price of Canon EOS 80D, can you help?",
        "Canon EOS 80D pricing, please?",
        "What's the pricing like for Canon EOS 80D?",
        "Do you have any information on Canon EOS 80D pricing?",
        "Price for Canon EOS 80D, please?",
        "Can you give me a quote for Canon EOS 80D?",
        "How much do I need to budget for Canon EOS 80D?",
        "Canon EOS 80D - how much does it go for?",
        "Canon EOS 80D - what's the cost?",
        "What's the market price for Canon EOS 80D?",
        "How much money should I prepare for Canon EOS 80D?",
        "What's the current price for Canon EOS 80D?",
        "Can you provide pricing details for Canon EOS 80D?",
        "Canon EOS 80D - how much will it set me back?"
      ],
      "responses": ["The price of Canon EOS 80D DSLR Camera is $929.99."],
      "context_set": ""
    },

    {
      "tag": "iphone_13_pro_price",
      "questions": [
        "iPhone 13 Pro price?",
        "How much is iPhone 13 Pro?",
        "Price of iPhone 13 Pro?",
        "What is the price of iPhone 13 Pro?",
        "How expensive is iPhone 13 Pro?",
        "What's the cost of iPhone 13 Pro?",
        "Can you tell me the price of iPhone 13 Pro?",
        "What's the price tag on iPhone 13 Pro?",
        "iPhone 13 Pro - how much?",
        "What's the price range for iPhone 13 Pro?",
        "I'm interested in iPhone 13 Pro, what's the pricing?",
        "How affordable is iPhone 13 Pro?",
        "Is iPhone 13 Pro expensive?",
        "What's the price point for iPhone 13 Pro?",
        "I need to know the price of iPhone 13 Pro, can you help?",
        "iPhone 13 Pro pricing, please?",
        "What's the pricing like for iPhone 13 Pro?",
        "Do you have any information on iPhone 13 Pro pricing?",
        "Price for iPhone 13 Pro, please?",
        "Can you give me a quote for iPhone 13 Pro?",
        "How much do I need to budget for iPhone 13 Pro?",
        "iPhone 13 Pro - how much does it go for?",
        "iPhone 13 Pro - what's the cost?",
        "What's the market price for iPhone 13 Pro?",
        "How much money should I prepare for iPhone 13 Pro?",
        "What's the current price for iPhone 13 Pro?",
        "Can you provide pricing details for iPhone 13 Pro?",
        "iPhone 13 Pro - how much will it set me back?"
      ],
      "responses": ["The price of iPhone 13 Pro 256GB Memory is $599.99."],
      "context_set": ""
    },

    {
      "tag": "logitech_gaming_mouse_price",
      "questions": [
        "iPhone 13 Pro price?",
        "How much is iPhone 13 Pro?",
        "Price of iPhone 13 Pro?",
        "What is the price of iPhone 13 Pro?",
        "How expensive is iPhone 13 Pro?",
        "What's the cost of iPhone 13 Pro?",
        "Can you tell me the price of iPhone 13 Pro?",
        "What's the price tag on iPhone 13 Pro?",
        "iPhone 13 Pro - how much?",
        "What's the price range for iPhone 13 Pro?",
        "I'm interested in iPhone 13 Pro, what's the pricing?",
        "How affordable is iPhone 13 Pro?",
        "Is iPhone 13 Pro expensive?",
        "What's the price point for iPhone 13 Pro?",
        "I need to know the price of iPhone 13 Pro, can you help?",
        "iPhone 13 Pro pricing, please?",
        "What's the pricing like for iPhone 13 Pro?",
        "Do you have any information on iPhone 13 Pro pricing?",
        "Price for iPhone 13 Pro, please?",
        "Can you give me a quote for iPhone 13 Pro?",
        "How much do I need to budget for iPhone 13 Pro?",
        "iPhone 13 Pro - how much does it go for?",
        "iPhone 13 Pro - what's the cost?",
        "What's the market price for iPhone 13 Pro?",
        "How much money should I prepare for iPhone 13 Pro?",
        "What's the current price for iPhone 13 Pro?",
        "Can you provide pricing details for iPhone 13 Pro?",
        "iPhone 13 Pro - how much will it set me back?"
      ],
      "responses": ["The price of Logitech G-Series Gaming Mouse is $39.99."],
      "context_set": ""
    },

    {
      "tag": "goodbye",
      "questions": [
        "cya",
        "see you",
        "bye bye",
        "See you later",
        "Goodbye",
        "I am Leaving",
        "Bye",
        "Have a Good day",
        "talk to you later",
        "ttyl",
        "i got to go",
        "gtg",
        "farewell",
        "adios",
        "catch you later",
        "take care",
        "until next time",
        "so long",
        "see you soon"
      ],
      "responses": [
        "Sad to see you go :(",
        "Talk to you later",
        "Goodbye!",
        "Come back soon",
        "See you next time!",
        "Take care!",
        "Farewell!",
        "Until we meet again!",
        "Have a great day!",
        "Goodbye for now!",
        "Adios!",
        "Catch you later!",
        "Bye bye, take care!",
        "So long, partner!",
        "Safe travels!",
        "Take it easy!"
      ],
      "context_set": ""
    },
    {
      "tag": "Payment Methods",
      "questions": [
        "How can I pay?",
        "What payment methods do you accept?",
        "Do you accept PayPal?",
        "Can I pay with cash on delivery?",
        "What are my payment options?",
        "Is PayPal accepted for transactions?",
        "Can I use credit/debit cards for payment?",
        "Do you offer payment plans?",
        "What currencies do you accept?",
        "Can I pay using mobile payment apps?",
        "Do you accept bank transfers?",
        "Do you accept international payments?",
        "Can I split payment between multiple methods?"
      ],
      "responses": [
        "We accept PayPal, credit/debit cards, and cash on delivery as payment methods.",
        "Yes, we accept PayPal for transactions.",
        "You can choose between PayPal or cash on delivery for payment.",
        "Yes, cash on delivery is available for selected areas.",
        "Our payment options include PayPal, credit/debit cards, and cash on delivery.",
        "Yes, you can pay using credit/debit cards.",
        "We offer cash on delivery and various online payment methods.",
        "We don't currently offer payment plans.",
        "We accept payments in multiple currencies.",
        "We accept payments through selected mobile payment apps.",
        "We do not accept bank transfers at this time.",
        "Yes, we accept international payments.",
        "We do not currently support split payments."
      ]
    },
    {
      "tag": "Payment Policies",
      "questions": [
        "What is your payment policy?",
        "Are there any additional fees for certain payment methods?",
        "Are there any restrictions on payment methods?",
        "What happens if I need to cancel or change my payment method?",
        "Is there a deadline for payment?",
        "What happens if my payment fails?",
        "What is your refund policy?"
      ],
      "responses": [
        "Our payment policy ensures secure and convenient transactions.",
        "There may be additional fees for certain payment methods. Please check our website for details.",
        "Please check our website for any restrictions on payment methods.",
        "If you need to cancel or change your payment method, please contact customer service.",
        "Payment is typically due upon order placement.",
        "If your payment fails, please contact your bank or try another payment method.",
        "Please review our refund policy on our website."
      ]
    },
    {
      "tag": "Transaction Process",
      "questions": [
        "How do I complete the transaction?",
        "What are the steps to make a payment?"
      ],
      "responses": [
        "To complete the transaction, select your preferred payment method at checkout.",
        "To make a payment, proceed to checkout and follow the instructions."
      ]
    }
  ]
}
